getmem/__init__.py
getmem/main.py
getmem-1.3.data/scripts/getmem
getmem-1.3.dist-info/LICENCE.txt
getmem-1.3.dist-info/METADATA
getmem-1.3.dist-info/WHEEL
getmem-1.3.dist-info/top_level.txt
getmem-1.3.dist-info/RECORD
