Metadata-Version: 2.1
Name: getmem
Version: 1.3
Summary: Find out the biggest files in your computer!
Home-page: UNKNOWN
Author: Shaurya Pratap Singh
Author-email: shaurya.p.singh21@gmail.com
License: MIT
Platform: UNKNOWN
Classifier: License :: OSI Approved :: MIT License
Classifier: Programming Language :: Python :: 3
Classifier: Programming Language :: Python :: 3.7
